LICENSE
README.md
setup.cfg
setup.py
deqs/__init__.py
deqs/calculator.py
deqs/methods.py
deqs/obj.py
deqs/tools.py
deqs/types.py
deqs.egg-info/PKG-INFO
deqs.egg-info/SOURCES.txt
deqs.egg-info/dependency_links.txt
deqs.egg-info/top_level.txt