Metadata-Version: 2.4
Name: deqs
Version: 0.0.2
Summary: Simple library for solving systems of differential equations
Home-page: https://github.com/belinmikh/deqs
Author: belinmikh
Author-email: belinma@yandex.ru
Project-URL: GitHub, https://github.com/belinmikh
License-File: LICENSE
Dynamic: author
Dynamic: author-email
Dynamic: description
Dynamic: description-content-type
Dynamic: home-page
Dynamic: license-file
Dynamic: project-url
Dynamic: summary
